mcp_baselib-1.0.3.dist-info/licenses/LICENSE
mcplib/__init__.py
mcplib/server.py
mcp_baselib-1.0.3.dist-info/METADATA
mcp_baselib-1.0.3.dist-info/WHEEL
mcp_baselib-1.0.3.dist-info/top_level.txt
mcp_baselib-1.0.3.dist-info/RECORD
