Metadata-Version: 2.4
Name: mcp-baselib
Version: 1.0.3
Summary: MCP utilities
Author: Gregor Roth
Author-email: gregor.roth@web.de
Classifier: Programming Language :: Python :: 3
Classifier: Operating System :: OS Independent
Requires-Python: >=3.11
License-File: LICENSE
Requires-Dist: mcp>=1.25.0
Requires-Dist: zeroconf>=0.131.0
Dynamic: license-file
